Workbook

Sheet Config
A1: key | B1: value
A2: reference_manufacturer | B2: KALDEWEI
A3: reference_product | B3: FLOWLINE ZERO
A4: target_length_mm | B4: 1200
A5: length_tolerance_mm | B5: 100
A6: include_cuttable | B6: yes
A7: scope | B7: complete system
A8: required_min_flow_rate_lps | B8: 0.8
A9: pricing_market | B9: DE
A10: currency | B10: EUR
A11: shipping_included | B11: no
A12: pricing_sources_priority | B12: Reuter.de; Megabad.de; Hornbach.de
A13: pricing_rule | B13: lowest normal price; shipping excluded; may use other DE sources as fallback
A14: non_complete_system_handling | B14: keep in registry; mark as not_complete_system; exclude from benchmark
A15: generated_utc | B15: 2026-01-02T12:58:39Z
A16: promo_handling | B16: prefer non-promo; if only promo available, use promo and flag
A17: price_output_fields | B17: min_price_de_eur = chosen; additional fields: min_price_de_eur_any, min_price_de_eur_regular
A18: match_priority | B18: closest_equivalent
A19: flow_rate_filtering | B19: collect_only (filter during scoring)
A20: material_inference | B20: allowed (store inferred flag + note)
A21: length_tolerance_mm | B21: 100
A22: include_cuttable | B22: yes
A24: Scoring configuration references
A25: Equivalence weights sheet | B25: Equivalence_Weights
A26: Final scoring weights sheet | B26: Final_Scoring_Weights
A27: Settings sheet | B27: Scoring_Settings
A28: Last template update (UTC) | B28: 2026-01-13T10:21:30Z

Sheet Pricing_Sources
A1: retailer | B1: priority | C1: notes
A2: Reuter.de | B2: 1 | C2: Preferred; may require headless/browser automation due to bot protection.
A3: Megabad.de | B3: 2 | C3: Preferred; often lists sets and technical text.
A4: Hornbach.de | B4: 3 | C4: Preferred; often modular pricing via component sum.
A5: Fallback_DE | B5: 99 | C5: Allowed: any reputable German retailer when preferred sources lack a matching variant.

Sheet Candidates_All
A1: manufacturer | B1: product_family | C1: product | D1: length_mode | E1: available_lengths_mm | F1: selected_length_mm | G1: length_delta_mm | H1: complete_system | I1: tileable | J1: outlet | K1: flow_rate_l_min | L1: material | M1: sealing_fleece | N1: sources | O1: captured_ts | P1: target_length_mm | Q1: length_tolerance_mm | R1: eligible_length_match | S1: system_completeness | T1: eligible_complete_system | U1: eligible_for_benchmark | V1: source_domain | W1: registry_generated_ts
A2: hansgrohe | B2: RainDrain | C2: RainDrain Compact – Complete set shower drain 1200 (56184800) | D2: fixed | E2: 1200 | F2: 1200 | G2: 0 | H2: yes | I2: unknown | J2: horizontal | K2: up to 37 | L2: Stainless steel 304 (1.4301) + ABS (trap) | M2: pre-assembled sealing membrane | N2: https://www.hansgrohe.com/articledetail-raindrain-compact-complete-set-shower-drain-1200-for-standard-installation-56184800 | O2: 2026-01-02T11:58:03Z | P2: 1200 | Q2: 100 | R2: TRUE | S2: complete_set | T2: TRUE | U2: TRUE | V2: www.hansgrohe.com | W2: 2026-01-02T12:31:56Z
A3: hansgrohe | B3: RainDrain | C3: RainDrain Allround – Complete set shower drain 1200 (56190800) | D3: fixed | E3: 1200 | F3: 1200 | G3: 0 | H3: yes | I3: unknown | J3: horizontal | K3: up to 33 (standard) / 32 (flat) | L3: Stainless steel 304 (1.4301) | M3: pre-assembled sealing membrane | N3: https://www.hansgrohe.com/articledetail-raindrain-allround-complete-set-shower-drain-1200-for-standard-flat-installation-56190800 | O3: 2026-01-02T11:58:03Z | P3: 1200 | Q3: 100 | R3: TRUE | S3: complete_set | T3: TRUE | U3: TRUE | V3: www.hansgrohe.com | W3: 2026-01-02T12:31:56Z
A4: hansgrohe | B4: RainDrain | C4: RainDrain Go – Complete set shower drain 1200 tileable rear cover (56276670) | D4: fixed | E4: 1200 | F4: 1200 | G4: 0 | H4: yes | I4: yes | J4: unknown | K4: unknown | L4: unknown | M4: unknown | N4: https://www.hansgrohe.com/articledetail-raindrain-go-complete-set-shower-drain-1200-tileable-rear-cover-standard-flat-installation-56276670 | O4: 2026-01-02T11:58:03Z | P4: 1200 | Q4: 100 | R4: TRUE | S4: complete_set | T4: TRUE | U4: TRUE | V4: www.hansgrohe.com | W4: 2026-01-02T12:31:56Z
A5: hansgrohe | B5: RainDrain | C5: RainDrain Original – Finish set shower drain 1200 (56201800) | D5: fixed | E5: 1200 | F5: 1200 | G5: 0 | H5: no (finish set; required parts listed) | I5: no | J5: unknown | K5: up to 49 | L5: unknown | M5: membrane included | N5: https://www.hansgrohe.com/articledetail-raindrain-original-finish-set-shower-drain-1200-56201800 | O5: 2026-01-02T11:58:03Z | P5: 1200 | Q5: 100 | R5: TRUE | S5: not_complete_system | T5: FALSE | U5: FALSE | V5: www.hansgrohe.com | W5: 2026-01-02T12:31:56Z
A6: Schlüter-Systems | B6: KERDI-LINE | C6: KERDI-LINE-G3 – Complete set (height 78 mm; lengths include up to 1200) | D6: range | E6: up to 1200 | F6: 1200 | G6: 0 | H6: yes | I6: unknown | J6: unknown (depends configuration) | K6: unknown | L6: unknown | M6: unknown (verify in downloads) | N6: https://eu.schluter.com/en-GB/drainage-312/e/33224/kerdi-line-g3 | O6: 2026-01-02T11:58:03Z | P6: 1200 | Q6: 100 | R6: TRUE | S6: complete_set | T6: TRUE | U6: TRUE | V6: eu.schluter.com | W6: 2026-01-02T12:31:56Z
A7: Schlüter-Systems | B7: KERDI-LINE | C7: KERDI-LINE-V – Complete set for vertical linear drainage | D7: unknown | E7: unknown | H7: yes | I7: unknown | J7: vertical | K7: unknown | L7: unknown | M7: unknown | N7: https://eu.schluter.com/en-GB/drainage-312/e/22137/kerdi-line-v | O7: 2026-01-02T11:58:03Z | P7: 1200 | Q7: 100 | R7: FALSE | S7: complete_set | T7: TRUE | U7: FALSE | V7: eu.schluter.com | W7: 2026-01-02T12:31:56Z
A8: Schlüter-Systems | B8: KERDI-LINE-VARIO | C8: KERDI-LINE-VARIO-COVE – drainage profile 120/180 cm, cuttable | D8: cuttable | E8: 1200;1800 | F8: 1200 | G8: 0 | H8: no (profile only) | I8: unknown | J8: n/a (profile) | K8: unknown | L8: unknown | M8: depends on drainage body | N8: https://eu.schluter.com/en-DE/drainage-312/e/22408/kerdi-line-vario-cove | O8: 2026-01-02T11:58:03Z | P8: 1200 | Q8: 100 | R8: TRUE | S8: not_complete_system | T8: FALSE | U8: FALSE | V8: eu.schluter.com | W8: 2026-01-02T12:31:56Z
A9: Schlüter-Systems | B9: KERDI-LINE-VARIO | C9: KERDI-LINE-VARIO-WAVE – drainage profile 120/180 cm, cuttable | D9: cuttable | E9: 1200;1800 | F9: 1200 | G9: 0 | H9: no (profile only) | I9: unknown | J9: n/a (profile) | K9: unknown | L9: V4A option mentioned (variant) | M9: depends on drainage body | N9: https://eu.schluter.com/en-GB/drainage-312/e/22418/kerdi-line-vario-wave | O9: 2026-01-02T11:58:03Z | P9: 1200 | Q9: 100 | R9: TRUE | S9: not_complete_system | T9: FALSE | U9: FALSE | V9: eu.schluter.com | W9: 2026-01-02T12:31:56Z
A10: Geberit | B10: CleanLine | C10: CleanLine20 – shower channel (cut-to-length) | D10: cuttable | E10: cuttable (product family) | F10: 1200 | G10: 0 | H10: no (channel; installation set required) | I10: yes/variants | J10: depends on drain unit | K10: see installation set (e.g., 0.4 l/s @ 20mm head for DN40 set) | L10: stainless steel (grade not stated here) | M10: installation set may include non-woven sealing fabric | N10: https://catalog.geberit-global.com/en-SA/product/PRO_170946 | https://cdn.data.geberit.com/documents/966.838.00.0_03.pdf | O10: 2026-01-02T11:58:03Z | P10: 1200 | Q10: 100 | R10: TRUE | S10: not_complete_system | T10: FALSE | U10: FALSE | V10: catalog.geberit-global.com | W10: 2026-01-02T12:31:56Z
A11: TECE | B11: TECEdrainline | C11: TECEdrainline – modular shower channel (nominal lengths 700–1200) | D11: range | E11: 700–1200 | F11: 1200 | G11: 0 | H11: modular (channel + drain body) | I11: options | J11: unknown | K11: unknown | L11: varies; Evo with factory-fitted sealing collar | M11: yes (Evo: factory-fitted sealing collar) | N11: https://www.tece.com/en/drainage/tecedrainline-shower-channel/modular-system | O11: 2026-01-02T11:58:03Z | P11: 1200 | Q11: 100 | R11: TRUE | S11: modular_complete | T11: TRUE | U11: TRUE | V11: www.tece.com | W11: 2026-01-02T12:31:56Z
A12: Viega | B12: Advantix Vario | C12: Advantix Vario – shower channel variable 300–1200 (cuttable) | D12: cuttable | E12: 300–1200 | F12: 1200 | G12: 0 | H12: yes (per brochure: delivered with accessories) | I12: options (depending on grate/inlay) | J12: unknown | K12: unknown | L12: stainless variants; multiple colour variants | M12: unknown | N12: https://www.viega.com/content/dam/viegadm/en/temp/download_assets/com/734374_brochure_advantixvario_2_int_net.pdf | O12: 2026-01-02T11:58:03Z | P12: 1200 | Q12: 100 | R12: TRUE | S12: complete_set | T12: TRUE | U12: TRUE | V12: www.viega.com | W12: 2026-01-02T12:31:56Z
A13: Easy Drain | B13: Multi TAF | C13: Multi TAF – complete set, lengths 500–2000 (includes 1200), WPS pre-assembled | D13: range | E13: 500–2000 | F13: 1200 | G13: 0 | H13: yes | I13: option | J13: unknown | K13: according to EN 1253 | L13: unknown | M13: yes (pre-assembled sealing membrane WPS) | N13: https://www.easydrain.com/product/multi-taf/ | O13: 2026-01-02T11:58:03Z | P13: 1200 | Q13: 100 | R13: TRUE | S13: complete_set | T13: TRUE | U13: TRUE | V13: www.easydrain.com | W13: 2026-01-02T12:31:56Z
A14: Easy Drain | B14: Nano Wall | C14: Nano Wall – complete set, lengths 700–1200, drainage capacity 33 l/min | D14: range | E14: 700–1200 | F14: 1200 | G14: 0 | H14: yes | I14: tile adjustable frame | J14: unknown | K14: 33 | L14: unknown | M14: yes (Water Protection System) | N14: https://www.easydrain.com/product/nano-wall/ | O14: 2026-01-02T11:58:03Z | P14: 1200 | Q14: 100 | R14: TRUE | S14: complete_set | T14: TRUE | U14: TRUE | V14: www.easydrain.com | W14: 2026-01-02T12:31:56Z
A15: Easy Drain | B15: S-line | C15: S-line – complete set, lengths 700–1200, WPS pre-assembled | D15: range | E15: 700–1200 | F15: 1200 | G15: 0 | H15: yes | I15: unknown | J15: unknown | K15: according to EN 1253 | L15: unknown | M15: yes (WPS pre-assembled) | N15: https://www.easydrain.com/product/s-line/ | O15: 2026-01-02T11:58:03Z | P15: 1200 | Q15: 100 | R15: TRUE | S15: complete_set | T15: TRUE | U15: TRUE | V15: www.easydrain.com | W15: 2026-01-02T12:31:56Z
A16: Easy Drain | B16: Modulo Basic | C16: Modulo Basic – complete set, lengths 500–1200, horizontal outlet, EN 1253 | D16: range | E16: 500–1200 | F16: 1200 | G16: 0 | H16: yes | I16: options | J16: horizontal | K16: according to EN 1253 | L16: unknown | M16: WPS (implied) | N16: https://www.easydrain.com/product/modulo-basic-polished-grate/ | O16: 2026-01-02T11:58:03Z | P16: 1200 | Q16: 100 | R16: TRUE | S16: complete_set | T16: TRUE | U16: TRUE | V16: www.easydrain.com | W16: 2026-01-02T12:31:56Z
A17: Dallmer | B17: CeraLine | C17: CeraLine F – shower channel 1200 mm DN50 (horizontal outlet), DIN EN 1253 mentioned | D17: fixed | E17: 1200 | F17: 1200 | G17: 0 | H17: yes | I17: unknown | J17: horizontal | K17: unknown | L17: see specification on page | M17: unknown | N17: https://www.dallmer.com/int/produkte/520074_shower-channel-CeraLine-F-1200-mm-DN-50.php | O17: 2026-01-02T11:58:03Z | P17: 1200 | Q17: 100 | R17: TRUE | S17: complete_set | T17: TRUE | U17: TRUE | V17: www.dallmer.com | W17: 2026-01-02T12:31:56Z
A18: Dallmer | B18: CeraLine | C18: CeraLine W – shower channel 1200 mm DN50 (wall installation, horizontal outlet), DIN EN 1253 mentioned | D18: fixed | E18: 1200 | F18: 1200 | G18: 0 | H18: yes | I18: unknown | J18: horizontal | K18: unknown | L18: see specification on page | M18: unknown | N18: https://www.dallmer.com/be/produkte/520173_shower-channel-ceraline-w-1200-mm-dn-50.php | O18: 2026-01-02T11:58:03Z | P18: 1200 | Q18: 100 | R18: TRUE | S18: complete_set | T18: TRUE | U18: TRUE | V18: www.dallmer.com | W18: 2026-01-02T12:31:56Z
A19: Alcadrain | B19: Plastic linear shower drains | C19: APZ12/APZ22 Optimal – max length 1050 (nearest to 1200) | D19: fixed variants | E19: 750;850;950;1050 | F19: 1050 | G19: -150 | H19: modular (grid may be separate) | I19: option (grids for embedding tiles) | J19: Ø50 | K19: 63 | L19: plastic body | M19: unknown | N19: https://www.alcadrain.com/downloads?catid=276&id=11907%3Aplastic-linear-shower-drains&task=download.send | O19: 2026-01-02T11:58:03Z | P19: 1200 | Q19: 100 | R19: FALSE | S19: modular_complete | T19: TRUE | U19: FALSE | V19: www.alcadrain.com | W19: 2026-01-02T12:31:56Z
... A27: SCHÜTTE | B27: Duschrinne | C27: SCHÜTTE Duschrinne 800 mm mit Edelstahlabdeckung (ID 10025) – found in Verkaufshits list | D27: fixed | E27: 800 | F27: 800 | G27: -400 | H27: unknown (retail-style SKU) | I27: unknown | J27: unknown | K27: unknown | L27: unknown | M27: unknown | N27: https://fjschuette.com/de/verkaufshits?page=5 | O27: 2026-01-02T12:31:56Z | P27: 1200 | Q27: 100 | R27: FALSE | S27: not_complete_system | T27: FALSE | U27: FALSE | V27: fjschuette.com | W27: 2026-01-02T12:31:56Z

Sheet Excluded
A1: manufacturer | B1: product_family | C1: product | D1: selected_length_mm | E1: length_delta_mm | F1: system_completeness | G1: eligible_length_match | H1: eligible_complete_system | I1: eligible_for_benchmark | J1: exclusion_reason | K1: sources
A2: hansgrohe | B2: RainDrain | C2: RainDrain Original – Finish set shower drain 1200 (56201800) | D2: 1200 | E2: 0 | F2: not_complete_system | G2: TRUE | H2: FALSE | I2: FALSE | J2: not_complete_system | K2: https://www.hansgrohe.com/articledetail-raindrain-original-finish-set-shower-drain-1200-56201800
A3: Schlüter-Systems | B3: KERDI-LINE | C3: KERDI-LINE-V – Complete set for vertical linear drainage | F3: complete_set | G3: FALSE | H3: TRUE | I3: FALSE | J3: length_unknown | K3: https://eu.schluter.com/en-GB/drainage-312/e/22137/kerdi-line-v
A4: Schlüter-Systems | B4: KERDI-LINE-VARIO | C4: KERDI-LINE-VARIO-COVE – drainage profile 120/180 cm, cuttable | D4: 1200 | E4: 0 | F4: not_complete_system | G4: TRUE | H4: FALSE | I4: FALSE | J4: not_complete_system | K4: https://eu.schluter.com/en-DE/drainage-312/e/22408/kerdi-line-vario-cove
A5: Schlüter-Systems | B5: KERDI-LINE-VARIO | C5: KERDI-LINE-VARIO-WAVE – drainage profile 120/180 cm, cuttable | D5: 1200 | E5: 0 | F5: not_complete_system | G5: TRUE | H5: FALSE | I5: FALSE | J5: not_complete_system | K5: https://eu.schluter.com/en-GB/drainage-312/e/22418/kerdi-line-vario-wave
A6: Geberit | B6: CleanLine | C6: CleanLine20 – shower channel (cut-to-length) | D6: 1200 | E6: 0 | F6: not_complete_system | G6: TRUE | H6: FALSE | I6: FALSE | J6: not_complete_system | K6: https://catalog.geberit-global.com/en-SA/product/PRO_170946 | https://cdn.data.geberit.com/documents/966.838.00.0_03.pdf
A7: Alcadrain | B7: Plastic linear shower drains | C7: APZ12/APZ22 Optimal – max length 1050 (nearest to 1200) | D7: 1050 | E7: -150 | F7: modular_complete | G7: FALSE | H7: TRUE | I7: FALSE | J7: out_of_length_tolerance | K7: https://www.alcadrain.com/downloads?catid=276&id=11907%3Aplastic-linear-shower-drains&task=download.send
A8: hansgrohe | B8: RainDrain | C8: RainDrain Flex – Vrchní sada sprchového žlabu 1200 (56047800) – zkracovatelné | D8: 1200 | E8: 0 | F8: not_complete_system | G8: TRUE | H8: FALSE | I8: FALSE | J8: not_complete_system | K8: https://www.hansgrohe.cz/articledetail-raindrain-flex-vrchni-sada-sprchoveho-zlabu-1200-zkracovatelneho-pro-instalaci-volne-na-plochu-56047800
A9: hansgrohe | B9: RainDrain | C9: RainDrain Match – Vrchní sada sprchového žlabu 1200 (56042800) | D9: 1200 | E9: 0 | F9: not_complete_system | G9: TRUE | H9: FALSE | I9: FALSE | J9: not_complete_system | K9: https://www.hansgrohe.cz/articledetail-raindrain-match-vrchni-sada-sprchoveho-zlabu-1200-s-vyskove-stavitelnym-ramem-56042800
A10: SCHÜTTE | B10: Duschrinne | C10: SCHÜTTE Duschrinne 800 mm mit Edelstahlabdeckung (ID 10025) – found in Verkaufshits list | D10: 800 | E10: -400 | F10: not_complete_system | G10: FALSE | H10: FALSE | I10: FALSE | J10: out_of_length_tolerance;not_complete_system | K10: https://fjschuette.com/de/verkaufshits?page=5

Sheet Products
A1: product_id | B1: manufacturer | C1: product_family | D1: product_name | E1: target_length_mm | F1: selected_length_mm | G1: length_delta_mm | H1: product_url | I1: flow_rate_lps | J1: flow_rate_note | K1: material_v4a | L1: material_detail | M1: din_en_1253_cert | N1: din_18534_compliance | O1: height_adj_min_mm | P1: height_adj_max_mm | Q1: height_adj_note | R1: outlet_vertical | S1: outlet_side | T1: outlet_selectable | U1: sealing_fleece_preassembled | V1: colours_count | W1: colours_note | X1: bom_options_count | Y1: chosen_option_id | Z1: min_price_de_eur | AA1: price_basis | AB1: price_sources_used | AC1: price_timestamp_iso | AD1: notes | AE1: min_price_de_eur_any | AF1: min_price_de_eur_regular | AG1: price_promo_policy | AH1: installation_position | AI1: tileable | AJ1: outlet_dn | AK1: overall_height_mm | AL1: material_inferred | AM1: material_inference_note | AN1: equivalence_score | AO1: equivalence_notes | AP1: selected_option_id | AQ1: option_eligible | AR1: equivalence_score_0_100 | AS1: parameter_score_0_100 | AT1: final_score_0_100
A2: HANSGROHE-001 | B2: hansgrohe | C2: RainDrain | D2: RainDrain Compact – Complete set shower drain 1200 (56184800) | E2: 1200 | F2: 1200 | G2: 0 | H2: https://www.hansgrohe.com/articledetail-raindrain-compact-complete-set-shower-drain-1200-for-standard-installation-56184800 | AG2: prefer_non_promo
A3: HANSGROHE-002 | B3: hansgrohe | C3: RainDrain | D3: RainDrain Allround – Complete set shower drain 1200 (56190800) | E3: 1200 | F3: 1200 | G3: 0 | H3: https://www.hansgrohe.com/articledetail-raindrain-allround-complete-set-shower-drain-1200-for-standard-flat-installation-56190800 | AG3: prefer_non_promo
A4: HANSGROHE-003 | B4: hansgrohe | C4: RainDrain | D4: RainDrain Go – Complete set shower drain 1200 tileable rear cover (56276670) | E4: 1200 | F4: 1200 | G4: 0 | H4: https://www.hansgrohe.com/articledetail-raindrain-go-complete-set-shower-drain-1200-tileable-rear-cover-standard-flat-installation-56276670 | AG4: prefer_non_promo
A5: SCHLÜTER-SYSTEMS-004 | B5: Schlüter-Systems | C5: KERDI-LINE | D5: KERDI-LINE-G3 – Complete set (height 78 mm; lengths include up to 1200) | E5: 1200 | F5: 1200 | G5: 0 | H5: https://eu.schluter.com/en-GB/drainage-312/e/33224/kerdi-line-g3 | AG5: prefer_non_promo
A6: TECE-005 | B6: TECE | C6: TECEdrainline | D6: TECEdrainline – modular shower channel (nominal lengths 700–1200) | E6: 1200 | F6: 1200 | G6: 0 | H6: https://www.tece.com/en/drainage/tecedrainline-shower-channel/modular-system | AG6: prefer_non_promo
A7: VIEGA-006 | B7: Viega | C7: Advantix Vario | D7: Advantix Vario – shower channel variable 300–1200 (cuttable) | E7: 1200 | F7: 1200 | G7: 0 | H7: https://www.viega.com/content/dam/viegadm/en/temp/download_assets/com/734374_brochure_advantixvario_2_int_net.pdf | AG7: prefer_non_promo
A8: EASY_DRAIN-007 | B8: Easy Drain | C8: Multi TAF | D8: Multi TAF – complete set, lengths 500–2000 (includes 1200), WPS pre-assembled | E8: 1200 | F8: 1200 | G8: 0 | H8: https://www.easydrain.com/product/multi-taf/ | AG8: prefer_non_promo
A9: EASY_DRAIN-008 | B9: Easy Drain | C9: Nano Wall | D9: Nano Wall – complete set, lengths 700–1200, drainage capacity 33 l/min | E9: 1200 | F9: 1200 | G9: 0 | H9: https://www.easydrain.com/product/nano-wall/ | AG9: prefer_non_promo
A10: EASY_DRAIN-009 | B10: Easy Drain | C10: S-line | D10: S-line – complete set, lengths 700–1200, WPS pre-assembled | E10: 1200 | F10: 1200 | G10: 0 | H10: https://www.easydrain.com/product/s-line/ | AG10: prefer_non_promo
A11: EASY_DRAIN-010 | B11: Easy Drain | C11: Modulo Basic | D11: Modulo Basic – complete set, lengths 500–1200, horizontal outlet, EN 1253 | E11: 1200 | F11: 1200 | G11: 0 | H11: https://www.easydrain.com/product/modulo-basic-polished-grate/ | AG11: prefer_non_promo
A12: DALLMER-011 | B12: Dallmer | C12: CeraLine | D12: CeraLine F – shower channel 1200 mm DN50 (horizontal outlet), DIN EN 1253 mentioned | E12: 1200 | F12: 1200 | G12: 0 | H12: https://www.dallmer.com/int/produkte/520074_shower-channel-CeraLine-F-1200-mm-DN-50.php | AG12: prefer_non_promo
A13: DALLMER-012 | B13: Dallmer | C13: CeraLine | D13: CeraLine W – shower channel 1200 mm DN50 (wall installation, horizontal outlet), DIN EN 1253 mentioned | E13: 1200 | F13: 1200 | G13: 0 | H13: https://www.dallmer.com/be/produkte/520173_shower-channel-ceraline-w-1200-mm-dn-50.php | AG13: prefer_non_promo
... A18: GEBERIT-017 | B18: Geberit | C18: CleanLine | D18: Sprchový kanálek Geberit CleanLine80 (cuttable) – catalog CZ | E18: 1200 | F18: 1200 | G18: 0 | H18: https://catalog.geberit.cz/cs-CZ/product/PRO_1447036 | AG18: prefer_non_promo

Sheet BOM_Options
A1: product_id | B1: option_id | C1: option_name | D1: option_notes | E1: option_flow_rate_lps | F1: meets_min_flow_rate | G1: outlet_vertical | H1: outlet_side | I1: outlet_selectable | J1: height_adj_min_mm | K1: height_adj_max_mm | L1: material_v4a | M1: material_detail | N1: din_en_1253_cert | O1: din_18534_compliance | P1: sealing_fleece_preassembled | Q1: colours_count | R1: option_eligible | S1: eligibility_notes | U1: installation_position | V1: tileable | W1: outlet_dn | X1: overall_height_mm | Y1: material_inferred | Z1: material_inference_note | AA1: equivalence_score | AB1: equivalence_notes | AC1: selected_option_id
A2: HANSGROHE-001 | B2: OPT-001 | C2: Default (TBD) | D2: Auto-generated placeholder; agent will add all valid drain/body variants.
A3: HANSGROHE-002 | B3: OPT-001 | C3: Default (TBD) | D3: Auto-generated placeholder; agent will add all valid drain/body variants.
A4: HANSGROHE-003 | B4: OPT-001 | C4: Default (TBD) | D4: Auto-generated placeholder; agent will add all valid drain/body variants.
A5: SCHLÜTER-SYSTEMS-004 | B5: OPT-001 | C5: Default (TBD) | D5: Auto-generated placeholder; agent will add all valid drain/body variants.
A6: TECE-005 | B6: OPT-001 | C6: Default (TBD) | D6: Auto-generated placeholder; agent will add all valid drain/body variants.
A7: VIEGA-006 | B7: OPT-001 | C7: Default (TBD) | D7: Auto-generated placeholder; agent will add all valid drain/body variants.
A8: EASY_DRAIN-007 | B8: OPT-001 | C8: Default (TBD) | D8: Auto-generated placeholder; agent will add all valid drain/body variants.
A9: EASY_DRAIN-008 | B9: OPT-001 | C9: Default (TBD) | D9: Auto-generated placeholder; agent will add all valid drain/body variants.
A10: EASY_DRAIN-009 | B10: OPT-001 | C10: Default (TBD) | D10: Auto-generated placeholder; agent will add all valid drain/body variants.
A11: EASY_DRAIN-010 | B11: OPT-001 | C11: Default (TBD) | D11: Auto-generated placeholder; agent will add all valid drain/body variants.
A12: DALLMER-011 | B12: OPT-001 | C12: Default (TBD) | D12: Auto-generated placeholder; agent will add all valid drain/body variants.
A13: DALLMER-012 | B13: OPT-001 | C13: Default (TBD) | D13: Auto-generated placeholder; agent will add all valid drain/body variants.
... A18: GEBERIT-017 | B18: OPT-001 | C18: Default (TBD) | D18: Auto-generated placeholder; agent will add all valid drain/body variants.

Sheet Components
A1: product_id | B1: option_id | C1: component_role | D1: manufacturer | E1: component_name | F1: component_item_no | G1: EAN | H1: required_qty | I1: source_url | J1: notes

Sheet Offers
A1: offer_level | B1: item_key | C1: product_id | D1: option_id | E1: retailer | F1: price_eur | G1: price_includes_vat | H1: shipping_included | I1: is_promo | J1: offer_url | K1: captured_timestamp_iso | L1: notes

Sheet Evidence
A1: product_id | B1: option_id | C1: attribute | D1: value_normalized | E1: value_raw | F1: evidence_text | G1: source_url | H1: source_type | I1: page_or_section | J1: captured_timestamp_iso

Sheet Comparison
A1: product_id | B1: manufacturer | C1: product_family | D1: product_name | E1: selected_length_mm | F1: flow_rate_lps | G1: material_v4a | H1: din_en_1253_cert | I1: din_18534_compliance | J1: height_range_mm | K1: outlet_selectable | L1: sealing_fleece_preassembled | M1: colours_count | N1: min_price_de_eur | O1: target_length_mm | P1: length_delta_mm | Q1: installation_position | R1: tileable | S1: outlet_direction | T1: outlet_dn | U1: material_detail | V1: height_adj_min_mm | W1: height_adj_max_mm | X1: equivalence_score | Y1: selected_option_id | Z1: equivalence_score_0_100 | AA1: parameter_score_0_100 | AB1: final_score_0_100 | AC1: final_eq_component_0_100 | AD1: final_param_component_0_100 | AE1: contrib_equivalence | AF1: contrib_flow_rate | AG1: contrib_material_v4a | AH1: contrib_din_en_1253 | AI1: contrib_din_18534 | AJ1: contrib_height_adjustability | AK1: contrib_outlet_variants | AL1: contrib_sealing_fleece | AM1: contrib_colours | AN1: contrib_price
A2: =Products!A2 | B2: =Products!B2 | C2: =Products!C2 | D2: =Products!D2 | E2: =Products!F2 | F2: =Products!I2 | G2: =Products!K2 | H2: =Products!M2 | I2: =Products!N2 | J2: =IF(AND(Products!O2<>"",Products!P2<>""),TEXT(Products!O2,"0")&"–"&TEXT(Products!P2,"0"),"") | K2: =Products!S2 | L2: =Products!T2 | M2: =Products!U2 | N2: =Products!W2
A3: =Products!A3 | B3: =Products!B3 | C3: =Products!C3 | D3: =Products!D3 | E3: =Products!F3 | F3: =Products!I3 | G3: =Products!K3 | H3: =Products!M3 | I3: =Products!N3 | J3: =IF(AND(Products!O3<>"",Products!P3<>""),TEXT(Products!O3,"0")&"–"&TEXT(Products!P3,"0"),"") | K3: =Products!S3 | L3: =Products!T3 | M3: =Products!U3 | N3: =Products!W3
A4: =Products!A4 | B4: =Products!B4 | C4: =Products!C4 | D4: =Products!D4 | E4: =Products!F4 | F4: =Products!I4 | G4: =Products!K4 | H4: =Products!M4 | I4: =Products!N4 | J4: =IF(AND(Products!O4<>"",Products!P4<>""),TEXT(Products!O4,"0")&"–"&TEXT(Products!P4,"0"),"") | K4: =Products!S4 | L4: =Products!T4 | M4: =Products!U4 | N4: =Products!W4
A5: =Products!A5 | B5: =Products!B5 | C5: =Products!C5 | D5: =Products!D5 | E5: =Products!F5 | F5: =Products!I5 | G5: =Products!K5 | H5: =Products!M5 | I5: =Products!N5 | J5: =IF(AND(Products!O5<>"",Products!P5<>""),TEXT(Products!O5,"0")&"–"&TEXT(Products!P5,"0"),"") | K5: =Products!S5 | L5: =Products!T5 | M5: =Products!U5 | N5: =Products!W5
A6: =Products!A6 | B6: =Products!B6 | C6: =Products!C6 | D6: =Products!D6 | E6: =Products!F6 | F6: =Products!I6 | G6: =Products!K6 | H6: =Products!M6 | I6: =Products!N6 | J6: =IF(AND(Products!O6<>"",Products!P6<>""),TEXT(Products!O6,"0")&"–"&TEXT(Products!P6,"0"),"") | K6: =Products!S6 | L6: =Products!T6 | M6: =Products!U6 | N6: =Products!W6
A7: =Products!A7 | B7: =Products!B7 | C7: =Products!C7 | D7: =Products!D7 | E7: =Products!F7 | F7: =Products!I7 | G7: =Products!K7 | H7: =Products!M7 | I7: =Products!N7 | J7: =IF(AND(Products!O7<>"",Products!P7<>""),TEXT(Products!O7,"0")&"–"&TEXT(Products!P7,"0"),"") | K7: =Products!S7 | L7: =Products!T7 | M7: =Products!U7 | N7: =Products!W7
A8: =Products!A8 | B8: =Products!B8 | C8: =Products!C8 | D8: =Products!D8 | E8: =Products!F8 | F8: =Products!I8 | G8: =Products!K8 | H8: =Products!M8 | I8: =Products!N8 | J8: =IF(AND(Products!O8<>"",Products!P8<>""),TEXT(Products!O8,"0")&"–"&TEXT(Products!P8,"0"),"") | K8: =Products!S8 | L8: =Products!T8 | M8: =Products!U8 | N8: =Products!W8
A9: =Products!A9 | B9: =Products!B9 | C9: =Products!C9 | D9: =Products!D9 | E9: =Products!F9 | F9: =Products!I9 | G9: =Products!K9 | H9: =Products!M9 | I9: =Products!N9 | J9: =IF(AND(Products!O9<>"",Products!P9<>""),TEXT(Products!O9,"0")&"–"&TEXT(Products!P9,"0"),"") | K9: =Products!S9 | L9: =Products!T9 | M9: =Products!U9 | N9: =Products!W9
A10: =Products!A10 | B10: =Products!B10 | C10: =Products!C10 | D10: =Products!D10 | E10: =Products!F10 | F10: =Products!I10 | G10: =Products!K10 | H10: =Products!M10 | I10: =Products!N10 | J10: =IF(AND(Products!O10<>"",Products!P10<>""),TEXT(Products!O10,"0")&"–"&TEXT(Products!P10,"0"),"") | K10: =Products!S10 | L10: =Products!T10 | M10: =Products!U10 | N10: =Products!W10
A11: =Products!A11 | B11: =Products!B11 | C11: =Products!C11 | D11: =Products!D11 | E11: =Products!F11 | F11: =Products!I11 | G11: =Products!K11 | H11: =Products!M11 | I11: =Products!N11 | J11: =IF(AND(Products!O11<>"",Products!P11<>""),TEXT(Products!O11,"0")&"–"&TEXT(Products!P11,"0"),"") | K11: =Products!S11 | L11: =Products!T11 | M11: =Products!U11 | N11: =Products!W11
A12: =Products!A12 | B12: =Products!B12 | C12: =Products!C12 | D12: =Products!D12 | E12: =Products!F12 | F12: =Products!I12 | G12: =Products!K12 | H12: =Products!M12 | I12: =Products!N12 | J12: =IF(AND(Products!O12<>"",Products!P12<>""),TEXT(Products!O12,"0")&"–"&TEXT(Products!P12,"0"),"") | K12: =Products!S12 | L12: =Products!T12 | M12: =Products!U12 | N12: =Products!W12
A13: =Products!A13 | B13: =Products!B13 | C13: =Products!C13 | D13: =Products!D13 | E13: =Products!F13 | F13: =Products!I13 | G13: =Products!K13 | H13: =Products!M13 | I13: =Products!N13 | J13: =IF(AND(Products!O13<>"",Products!P13<>""),TEXT(Products!O13,"0")&"–"&TEXT(Products!P13,"0"),"") | K13: =Products!S13 | L13: =Products!T13 | M13: =Products!U13 | N13: =Products!W13
... A18: =Products!A18 | B18: =Products!B18 | C18: =Products!C18 | D18: =Products!D18 | E18: =Products!F18 | F18: =Products!I18 | G18: =Products!K18 | H18: =Products!M18 | I18: =Products!N18 | J18: =IF(AND(Products!O18<>"",Products!P18<>""),TEXT(Products!O18,"0")&"–"&TEXT(Products!P18,"0"),"") | K18: =Products!S18 | L18: =Products!T18 | M18: =Products!U18 | N18: =Products!W18

Sheet Reference_Profile
A1: attribute | B1: value | C1: note
A2: reference_product | B2: KALDEWEI FLOWLINE ZERO | C2: target baseline
A3: target_length_mm | B3: 1200 | C3: benchmark length
A4: installation_position | B4: wall_adjacent | C4: closest equivalent matching
A5: tileable | B5: no | C5: reference uses visible cover variants
A6: outlet_direction | B6: horizontal | C6: reference baseline
A7: outlet_dn | B7: DN50 | C7: reference baseline
A8: flow_rate_min_lps | B8: 0.8 | C8: standard requirement; filter later
A9: sealing_fleece_preassembled | B9: unknown | C9: to be verified from datasheet
A10: material_grade | B10: unknown | C10: derive if explicit (V4A/1.4404 etc.)

Sheet Equivalence_Weights
A1: key | B1: label | C1: weight_pct
A2: installation_type | B2: Typ instalace (wall/free) | C2: 17
A3: tileable | B3: Tileable / befliesbar | C3: 17
A4: outlet_type_dn | B4: Outlet (směr + DN) | C4: 17
A5: install_height | B5: Konstrukční/instalační výška | C5: 17
A6: sealing_fleece | B6: Sealing fleece / collar | C6: 16
A7: length_mode_match | B7: Délkový režim (fixed/cuttable/nearest) | C7: 16

Sheet Exclusion_Rules
A1: rule | B1: value | C1: note
A2: length_tolerance_mm | B2: 100 | C2: exclude if abs(delta) > tolerance
A3: complete_system_required | B3: yes | C3: exclude if not complete or modular_complete
A4: profile_only_handling | B4: keep_excluded | C4: keep but mark not_complete_system
A5: finish_set_handling | B5: keep_excluded | C5: keep but mark not_complete_system

Sheet Final_Scoring_Weights
A1: key | B1: label | C1: weight_pct | D1: enabled
A2: equivalence_overall | B2: Ekvivalentnost (vliv na pořadí) | C2: 20 | D2: TRUE
A3: flow_rate | B3: Průtok | C3: 15 | D3: TRUE
A4: material_v4a | B4: Materiál / V4A | C4: 15 | D4: TRUE
A5: din_en_1253 | B5: DIN EN 1253 | C5: 10 | D5: TRUE
A6: din_18534 | B6: DIN EN 18534 | C6: 10 | D6: TRUE
A7: height_adjustability | B7: Výšková nastavitelnost (rozsah) | C7: 10 | D7: TRUE
A8: outlet_variants | B8: Outlet varianty (selectable / 2 varianty / 1 varianta) | C8: 10 | D8: TRUE
A9: sealing_fleece_preassembled | B9: Sealing fleece předmontovaný | C9: 5 | D9: TRUE
A10: colours_count | B10: Počet barev/povrchů | C10: 5 | D10: TRUE
A11: sales_price | B11: Cena (DE) – zatím ignorováno | C11: 0 | D11: FALSE

Sheet Scoring_Settings
A1: setting | B1: value | C1: note
A2: unknown_penalty_score | B2: 0.3 | C2: Skóre pro unknown hodnoty (0–1)
A3: price_enabled | B3: FALSE | C3: Pricing modul aktivní
A4: inference_penalty_enabled | B4: FALSE | C4: Penalizace inferred hodnot (zatím ne)
A5: weights_mode | B5: pct_sum_100 | C5: Váhy v procentech se součtem 100
A6: run_update_recompute | B6: on_click | C6: Přepočet až po Run update
A7: outlet_scoring_mode | B7: multi_variant_supported | C7: Rozlišuje selectable vs 2 různé varianty
